django_scalar/__init__.py
django_scalar/app_settings.py
django_scalar/apps.py
django_scalar/get_filter_parameters.py
django_scalar/py.typed
django_scalar/urls.py
django_scalar/views.py
django_scalar/static/css/scalar.css
django_scalar/templates/django_scalar/scalar.html
django_scalar/tests/__init__.py
django_scalar/tests/conftest.py
django_scalar/tests/test_app_settings.py
django_scalar/tests/test_get_filter_parameters.py
django_scalar/tests/test_urls.py
django_scalar/tests/test_views.py
django_scalar-0.2.0.dist-info/METADATA
django_scalar-0.2.0.dist-info/WHEEL
django_scalar-0.2.0.dist-info/RECORD
